<title>Метакоманды</title>
<text>
  Внутри sqlite3 можно выполнять команды SQL или так называемые метакоманды (или dot-команды).
  К метакомандам относятся несколько специальных команд для работы с SQLite. Они относятся только к утилите sqlite3, а не к SQL языку. В конце этих команд ; ставить не нужно.
</text>
<picture>1.png</picture>
<table>
  <row>
    <col>.show</col>
    <col>Показывает текущие настройки заданных параметров</col>
  </row>
  <row>
    <col>.databases</col>
    <col>Показывает название баз данных и файлов</col>
  </row>
  <row>
    <col>.quit</col>
    <col>Выход из sqlite3</col>
  </row>
  <row>
    <col>.tables</col>
    <col>Показывает текущие таблицы</col>
  </row>
  <row>
    <col>.schema</col>
    <col>Отражает структуру таблицы</col>
  </row>
  <row>
    <col>.header</col>
    <col>Отобразить или скрыть шапку таблицы</col>
  </row>
  <row>
    <col>.mode</col>
    <col>Выбор режима отображения данных таблицы</col>
  </row>
  <row>
    <col>.dump</col>
    <col>Сделать копию базы данных в текстовом формате</col>
  </row>
</table>
    
  
